trading_Artur_test/__init__.py
trading_Artur_test/_version.py
trading_Artur_test/example.py
trading_Artur_test-0.0.12.dist-info/LICENSE
trading_Artur_test-0.0.12.dist-info/METADATA
trading_Artur_test-0.0.12.dist-info/WHEEL
trading_Artur_test-0.0.12.dist-info/top_level.txt
trading_Artur_test-0.0.12.dist-info/RECORD
