Metadata-Version: 2.1
Name: trading-Artur-test
Version: 0.0.12
Summary: A sample Python project
Home-page: UNKNOWN
Author: Artur
License: UNKNOWN
Platform: UNKNOWN
Classifier: Development Status :: 3 - Alpha
Requires-Python: >=3.6, <4
License-File: LICENSE
Requires-Dist: pandas (==1.3.1)
